optimizers_af/__init__.py
optimizers_af/test_functions.py
optimizers_af/tests.py
optimizers_af/logs/__init__.py
optimizers_af/logs/log_config.py
optimizers_af/logs/logged_object.py
optimizers_af/optimizers/__init__.py
optimizers_af/optimizers/_base.py
optimizers_af/optimizers/_bound_constrained.py
optimizers_af/optimizers/base.py
optimizers_af/optimizers/hj.py
optimizers_af/optimizers/pca.py
optimizers_af/optimizers/pso.py
optimizers_af/optimizers/rmo.py
optimizers_af/tests/__init__.py
optimizers_af/tests/hj.py
optimizers_af/tests/pca.py
optimizers_af/tests/rmo.py
optimizers_af-0.0.4.dist-info/LICENSE
optimizers_af-0.0.4.dist-info/METADATA
optimizers_af-0.0.4.dist-info/WHEEL
optimizers_af-0.0.4.dist-info/top_level.txt
optimizers_af-0.0.4.dist-info/RECORD
