Metadata-Version: 2.1
Name: optimizers-af
Version: 0.0.4
Summary: The package provides functions for optimizing objective functions.
Home-page: https://github.com/AlbertFarkhutdinov/optimizers_af
Author: Albert Farkhutdinov
Author-email: albertfarhutdinov@gmail.com
Classifier: Development Status :: 2 - Pre-Alpha
Classifier: Programming Language :: Python :: 3.11
Classifier: License :: OSI Approved :: MIT License
Classifier: Operating System :: OS Independent
Requires-Python: >=3.9
License-File: LICENSE
Requires-Dist: numpy (>1.23)
